chucknorris/__init__.py
chucknorris/pmxbot.py
chucknorris/pronoun.py
chucknorris/quips.py
chucknorris/quips.txt
chucknorris/test_plugin.py
chucknorris-2.9.0.dist-info/LICENSE
chucknorris-2.9.0.dist-info/METADATA
chucknorris-2.9.0.dist-info/WHEEL
chucknorris-2.9.0.dist-info/entry_points.txt
chucknorris-2.9.0.dist-info/top_level.txt
chucknorris-2.9.0.dist-info/RECORD
